docs/Makefile
docs/api_reference.rst
docs/changelog.rst
docs/conf.py
docs/contributing.rst
docs/examples.rst
docs/index.rst
docs/make.bat
docs/readme.rst
docs/classes/sparrowpy.RadiosityFast.rst
docs/classes/sparrowpy.RadiosityKang.rst
docs/modules/sparrowpy.brdf.rst
docs/modules/sparrowpy.geometry.rst
docs/modules/sparrowpy.sound_object.rst
sparrowpy/__init__.py
sparrowpy/brdf.py
sparrowpy/geometry.py
sparrowpy/sound_object.py
sparrowpy/classes/RadiosityFast.py
sparrowpy/classes/RadiosityKang.py
sparrowpy/form_factor/__init__.py
sparrowpy/form_factor/integration.py
sparrowpy/form_factor/kang.py
sparrowpy/form_factor/universal.py
sparrowpy/testing/__init__.py
sparrowpy/testing/exact_ff_solutions.py
sparrowpy/testing/stub_utils.py
sparrowpy/utils/__init__.py
sparrowpy/utils/blender.py
sparrowpy-1.0.1.dist-info/licenses/LICENSE
tests/__init__.py
tests/conftest.py
tests/test_DRadiosityFast.py
tests/test_DRadiosityFast_infinite_diffuse_plane.py
tests/test_DRadiosityFast_order.py
tests/test_DirectionalRadiosityFast.py
tests/test_Radiosity.py
tests/test_RadiosityDirectional.py
tests/test_blender_import.py
tests/test_brdf.py
tests/test_conftest.py
tests/test_multisource.py
tests/test_radiosity_geometry.py
tests/test_radiosity_polygon.py
tests/test_radiosity_sound_object.py
tests/test_soundSource_Directivity.py
tests/test_sparrowpy.py
tests/test_universal_formfactor.py
tests/test_visibility.py
tests/test_data/Genelec8020_DAF_2016_1x1.v17.ms.sofa
tests/test_data/ITA_Dodecahedron.sofa
tests/test_data/cube.blend
tests/test_data/cube.stl
tests/test_data/cube_blocked.blend
tests/test_data/cube_simple.blend
tests/test_data/cube_subdiv.blend
tests/test_data/disk_10sides.blend
tests/test_data/disk_72sides.blend
tests/test_data/ihta.E_sec_2.sofa
tests/test_data/reference_energy_exchange_size0.5.far
tests/test_data/reference_energy_exchange_size1.far
tests/test_data/reference_form_factor_parallel_size0.5.far
tests/test_data/reference_form_factor_parallel_size1.far
sparrowpy-1.0.1.dist-info/METADATA
sparrowpy-1.0.1.dist-info/WHEEL
sparrowpy-1.0.1.dist-info/top_level.txt
sparrowpy-1.0.1.dist-info/RECORD
