Metadata-Version: 2.4
Name: sparrowpy
Version: 1.0.1
Summary: Sound Propagation with Acoustic Radiosity for Realistic Outdoor Worlds.
Author: The sparrowpy developers
License-Expression: MIT
Project-URL: Tracker, https://github.com/sparrow-acoustics/sparrowpy/issues
Project-URL: Documentation, https://sparrowpy.readthedocs.io/
Project-URL: Download, https://pypi.org/project/sparrowpy/
Project-URL: Homepage, https://pyfar.org/
Project-URL: Source, https://github.com/sparrow-acoustics/sparrowpy
Project-URL: Changelog, https://github.com/sparrow-acoustics/sparrowpy/blob/main/CHANGELOG.md
Keywords: acoustics,radiosity,sound propagation,auralization
Classifier: Development Status :: 4 - Beta
Classifier: Intended Audience :: Science/Research
Classifier: Natural Language :: English
Classifier: Programming Language :: Python :: 3
Classifier: Programming Language :: Python :: 3.10
Classifier: Programming Language :: Python :: 3.11
Classifier: Programming Language :: Python :: 3.12
Classifier: Programming Language :: Python :: 3.13
Requires-Python: >=3.10
License-File: LICENSE
Requires-Dist: numpy<2
Requires-Dist: scipy
Requires-Dist: matplotlib
Requires-Dist: pyfar
Requires-Dist: sofar
Provides-Extra: blender
Requires-Dist: bpy; extra == "blender"
Provides-Extra: fast
Requires-Dist: numba; extra == "fast"
Provides-Extra: deploy
Requires-Dist: twine; extra == "deploy"
Requires-Dist: wheel; extra == "deploy"
Requires-Dist: build; extra == "deploy"
Requires-Dist: setuptools; extra == "deploy"
Requires-Dist: bump-my-version; extra == "deploy"
Requires-Dist: sparrowpy[fast]; extra == "deploy"
Requires-Dist: sparrowpy[blender]; extra == "deploy"
Provides-Extra: tests
Requires-Dist: pytest; extra == "tests"
Requires-Dist: pytest-cov; extra == "tests"
Requires-Dist: watchdog; extra == "tests"
Requires-Dist: ruff==0.9.*; extra == "tests"
Requires-Dist: coverage; extra == "tests"
Requires-Dist: watermark; extra == "tests"
Requires-Dist: ipykernel; extra == "tests"
Requires-Dist: sparrowpy[fast]; extra == "tests"
Requires-Dist: nbmake; extra == "tests"
Provides-Extra: docs
Requires-Dist: sphinx; extra == "docs"
Requires-Dist: autodocsumm>=0.2.14; extra == "docs"
Requires-Dist: pydata-sphinx-theme; extra == "docs"
Requires-Dist: sphinx_mdinclude; extra == "docs"
Requires-Dist: sphinx-design; extra == "docs"
Requires-Dist: sphinx-favicon; extra == "docs"
Requires-Dist: nbsphinx; extra == "docs"
Requires-Dist: sphinx_gallery; extra == "docs"
Requires-Dist: nbsphinx_link; extra == "docs"
Requires-Dist: ipython; extra == "docs"
Provides-Extra: dev
Requires-Dist: sparrowpy[blender,deploy,docs,tests]; extra == "dev"
Dynamic: license-file
